[
  {"from":"USA","to":"GBR","amount":85000000000,"type":"vc","label":"US → UK VC & PE"},
  {"from":"USA","to":"IND","amount":42000000000,"type":"vc","label":"US → India VC"},
  {"from":"USA","to":"ISR","amount":28000000000,"type":"vc","label":"US → Israel VC"},
  {"from":"USA","to":"CHN","amount":15000000000,"type":"vc","label":"US → China VC"},
  {"from":"USA","to":"DEU","amount":18000000000,"type":"vc","label":"US → Germany VC"},
  {"from":"USA","to":"CAN","amount":22000000000,"type":"vc","label":"US → Canada VC"},
  {"from":"USA","to":"BRA","amount":12000000000,"type":"vc","label":"US → Brazil VC"},
  {"from":"USA","to":"SGP","amount":15000000000,"type":"vc","label":"US → Singapore VC"},
  {"from":"USA","to":"JPN","amount":8000000000,"type":"vc","label":"US → Japan VC"},
  {"from":"USA","to":"FRA","amount":10000000000,"type":"vc","label":"US → France VC"},
  {"from":"GBR","to":"IND","amount":8000000000,"type":"vc","label":"UK → India VC"},
  {"from":"GBR","to":"DEU","amount":5000000000,"type":"vc","label":"UK → Germany VC"},
  {"from":"CHN","to":"SGP","amount":12000000000,"type":"fdi","label":"China → Singapore FDI"},
  {"from":"CHN","to":"IDN","amount":8000000000,"type":"fdi","label":"China → Indonesia FDI"},
  {"from":"CHN","to":"BRA","amount":6000000000,"type":"fdi","label":"China → Brazil FDI"},
  {"from":"CHN","to":"NGA","amount":4000000000,"type":"fdi","label":"China → Nigeria FDI"},
  {"from":"CHN","to":"AUS","amount":7000000000,"type":"fdi","label":"China → Australia FDI"},
  {"from":"JPN","to":"USA","amount":35000000000,"type":"fdi","label":"Japan → US FDI"},
  {"from":"JPN","to":"GBR","amount":12000000000,"type":"fdi","label":"Japan → UK FDI"},
  {"from":"JPN","to":"IND","amount":8000000000,"type":"fdi","label":"Japan → India FDI"},
  {"from":"SAU","to":"USA","amount":25000000000,"type":"swf","label":"Saudi PIF → US Investments"},
  {"from":"SAU","to":"GBR","amount":10000000000,"type":"swf","label":"Saudi PIF → UK Investments"},
  {"from":"SAU","to":"IND","amount":8000000000,"type":"swf","label":"Saudi PIF → India"},
  {"from":"ARE","to":"USA","amount":20000000000,"type":"swf","label":"UAE ADIA → US"},
  {"from":"ARE","to":"GBR","amount":15000000000,"type":"swf","label":"UAE → UK Investments"},
  {"from":"NOR","to":"USA","amount":50000000000,"type":"swf","label":"Norway Fund → US Equities"},
  {"from":"NOR","to":"GBR","amount":25000000000,"type":"swf","label":"Norway Fund → UK"},
  {"from":"NOR","to":"JPN","amount":15000000000,"type":"swf","label":"Norway Fund → Japan"},
  {"from":"NOR","to":"DEU","amount":12000000000,"type":"swf","label":"Norway Fund → Germany"},
  {"from":"NOR","to":"FRA","amount":10000000000,"type":"swf","label":"Norway Fund → France"},
  {"from":"SGP","to":"USA","amount":30000000000,"type":"swf","label":"GIC/Temasek → US"},
  {"from":"SGP","to":"CHN","amount":20000000000,"type":"swf","label":"GIC/Temasek → China"},
  {"from":"SGP","to":"IND","amount":12000000000,"type":"swf","label":"GIC/Temasek → India"},
  {"from":"MEX","to":"USA","amount":63000000000,"type":"remittance","label":"Mexico → US Remittances"},
  {"from":"IND","to":"ARE","amount":20000000000,"type":"remittance","label":"India ← UAE Workers"},
  {"from":"IND","to":"USA","amount":15000000000,"type":"remittance","label":"India ← US Workers"},
  {"from":"IND","to":"SAU","amount":12000000000,"type":"remittance","label":"India ← Saudi Workers"},
  {"from":"NGA","to":"USA","amount":6000000000,"type":"remittance","label":"Nigeria ← US Diaspora"},
  {"from":"NGA","to":"GBR","amount":5000000000,"type":"remittance","label":"Nigeria ← UK Diaspora"},
  {"from":"USA","to":"CHN","amount":150000000000,"type":"trade","label":"US → China Trade"},
  {"from":"CHN","to":"USA","amount":500000000000,"type":"trade","label":"China → US Exports"},
  {"from":"USA","to":"MEX","amount":320000000000,"type":"trade","label":"US ↔ Mexico Trade"},
  {"from":"USA","to":"CAN","amount":380000000000,"type":"trade","label":"US ↔ Canada Trade"},
  {"from":"DEU","to":"USA","amount":160000000000,"type":"trade","label":"Germany → US Exports"},
  {"from":"DEU","to":"CHN","amount":120000000000,"type":"trade","label":"Germany → China Exports"},
  {"from":"JPN","to":"CHN","amount":140000000000,"type":"trade","label":"Japan → China Trade"},
  {"from":"KOR","to":"CHN","amount":160000000000,"type":"trade","label":"Korea → China Trade"},
  {"from":"AUS","to":"CHN","amount":110000000000,"type":"trade","label":"Australia → China Exports"},
  {"from":"SAU","to":"CHN","amount":65000000000,"type":"trade","label":"Saudi → China Oil"},
  {"from":"SAU","to":"JPN","amount":30000000000,"type":"trade","label":"Saudi → Japan Oil"},
  {"from":"SAU","to":"KOR","amount":25000000000,"type":"trade","label":"Saudi → Korea Oil"}
]
